reasonflow/__init__.py
reasonflow/agents/__init__.py
reasonflow/agents/api_connector_agent.py
reasonflow/agents/custom_agent_builder.py
reasonflow/agents/custom_task_agent.py
reasonflow/agents/data_retrieval_agent.py
reasonflow/agents/llm_agent.py
reasonflow/agents/web_browser_agent.py
reasonflow/config/DBConfigLoader.py
reasonflow/config/__init__.py
reasonflow/config/db_config.yaml
reasonflow/config/reasontrack.yaml
reasonflow/integrations/__init__.py
reasonflow/integrations/api_key_manager.py
reasonflow/integrations/llm_integrations.py
reasonflow/integrations/rag_integrations.py
reasonflow/integrations/web_browser_integration.py
reasonflow/integrations/websocket_integration.py
reasonflow/observability/__init__.py
reasonflow/observability/basic_tracker.py
reasonflow/observability/metrics.py
reasonflow/observability/reasontrack_adapter.py
reasonflow/observability/reasontrack_management_initializer.py
reasonflow/observability/tracker.py
reasonflow/observability/tracker_factory.py
reasonflow/observability/tracking_interface.py
reasonflow/orchestrator/__init__.py
reasonflow/orchestrator/input_parser.py
reasonflow/orchestrator/state_manager.py
reasonflow/orchestrator/workflow_builder.py
reasonflow/orchestrator/workflow_engine.py
reasonflow/persistence/__init__.py
reasonflow/persistence/database.py
reasonflow/persistence/document_management.py
reasonflow/persistence/firebase_integration.py
reasonflow/persistence/object_storage.py
reasonflow/persistence/versioning.py
reasonflow/tasks/__init__.py
reasonflow/tasks/task.py
reasonflow/tasks/task_manager.py
reasonflow/tasks/task_types.py
reasonflow-0.2.1.dist-info/METADATA
reasonflow-0.2.1.dist-info/WHEEL
reasonflow-0.2.1.dist-info/top_level.txt
reasonflow-0.2.1.dist-info/RECORD
