Metadata-Version: 2.4
Name: reasonflow
Version: 0.2.1
Summary: Reasonflow - Workflow Orchestration Framework
Home-page: https://github.com/sunnybedi990/reasonflow
Author: Sunny Bedi
Author-email: sunnybedi990@gmail.com
Project-URL: Homepage, https://github.com/sunnybedi990/reasonflow
Project-URL: Documentation, https://reasonflow.readthedocs.io
Project-URL: Repository, https://github.com/sunnybedi990/reasonflow.git
Project-URL: Issues, https://github.com/sunnybedi990/reasonflow/issues
Classifier: Development Status :: 4 - Beta
Classifier: Intended Audience :: Developers
Classifier: License :: OSI Approved :: MIT License
Classifier: Operating System :: OS Independent
Classifier: Programming Language :: Python :: 3
Classifier: Programming Language :: Python :: 3.9
Classifier: Programming Language :: Python :: 3.10
Classifier: Programming Language :: Python :: 3.11
Classifier: Programming Language :: Python :: 3.12
Classifier: Topic :: Software Development :: Libraries :: Python Modules
Requires-Python: >=3.9
Requires-Dist: reasonchain>=0.1.0
Requires-Dist: networkx>=3.1
Requires-Dist: pyyaml>=6.0
Requires-Dist: requests>=2.31.0
Requires-Dist: aiohttp>=3.8.5
Requires-Dist: playwright>=1.40.0
Requires-Dist: beautifulsoup4>=4.12.0
Requires-Dist: lxml>=4.9.0
Requires-Dist: nltk>=3.8.1
Requires-Dist: textblob>=0.17.1
Requires-Dist: readability-lxml>=0.8.1
Requires-Dist: axe-selenium-python>=2.1.6
Provides-Extra: observability
Requires-Dist: prometheus-client>=0.17.1; extra == "observability"
Requires-Dist: opentelemetry-api>=1.20.0; extra == "observability"
Requires-Dist: opentelemetry-sdk>=1.20.0; extra == "observability"
Requires-Dist: opentelemetry-exporter-otlp>=1.20.0; extra == "observability"
Requires-Dist: influxdb-client>=1.38.0; extra == "observability"
Requires-Dist: elasticsearch>=8.10.1; extra == "observability"
Requires-Dist: elasticsearch-async>=6.2.0; extra == "observability"
Requires-Dist: confluent-kafka>=2.2.0; extra == "observability"
Requires-Dist: redis>=5.0.1; extra == "observability"
Requires-Dist: aioredis>=2.0.1; extra == "observability"
Requires-Dist: aiosmtplib>=2.0.0; extra == "observability"
Provides-Extra: ai
Requires-Dist: sentence-transformers>=2.2.2; extra == "ai"
Requires-Dist: faiss-cpu>=1.7.4; extra == "ai"
Requires-Dist: torch>=2.1.0; extra == "ai"
Requires-Dist: transformers>=4.36.0; extra == "ai"
Requires-Dist: numpy>=1.24.0; extra == "ai"
Requires-Dist: pandas>=2.1.0; extra == "ai"
Requires-Dist: scikit-learn>=1.3.0; extra == "ai"
Provides-Extra: docs
Requires-Dist: python-docx>=1.0.0; extra == "docs"
Requires-Dist: PyPDF2>=3.0.0; extra == "docs"
Requires-Dist: pdfplumber>=0.10.0; extra == "docs"
Requires-Dist: pytesseract>=0.3.10; extra == "docs"
Requires-Dist: pdf2image>=1.16.3; extra == "docs"
Requires-Dist: pillow>=10.0.0; extra == "docs"
Provides-Extra: vectors
Requires-Dist: pinecone-client>=2.2.4; extra == "vectors"
Requires-Dist: pymilvus>=2.3.1; extra == "vectors"
Requires-Dist: qdrant-client>=1.7.0; extra == "vectors"
Requires-Dist: weaviate-client>=3.25.0; extra == "vectors"
Provides-Extra: llm
Requires-Dist: openai>=1.3.0; extra == "llm"
Requires-Dist: anthropic>=0.7.0; extra == "llm"
Requires-Dist: groq>=0.4.0; extra == "llm"
Provides-Extra: api
Requires-Dist: fastapi>=0.105.0; extra == "api"
Requires-Dist: uvicorn>=0.24.0; extra == "api"
Requires-Dist: httpx>=0.25.0; extra == "api"
Requires-Dist: requests>=2.31.0; extra == "api"
Requires-Dist: aiohttp>=3.9.0; extra == "api"
Requires-Dist: websockets>=12.0; extra == "api"
Provides-Extra: storage
Requires-Dist: firebase-admin>=6.2.0; extra == "storage"
Requires-Dist: boto3>=1.34.0; extra == "storage"
Requires-Dist: minio>=7.2.0; extra == "storage"
Requires-Dist: cachetools>=5.3.0; extra == "storage"
Provides-Extra: dev
Requires-Dist: pytest>=7.4.0; extra == "dev"
Requires-Dist: pytest-asyncio>=0.23.0; extra == "dev"
Requires-Dist: pytest-cov>=4.1.0; extra == "dev"
Requires-Dist: black>=23.12.0; extra == "dev"
Requires-Dist: isort>=5.13.0; extra == "dev"
Requires-Dist: flake8>=6.1.0; extra == "dev"
Requires-Dist: mypy>=1.7.0; extra == "dev"
Requires-Dist: pre-commit>=3.6.0; extra == "dev"
Provides-Extra: docs-build
Requires-Dist: sphinx>=7.1.0; extra == "docs-build"
Requires-Dist: sphinx-rtd-theme>=1.3.0; extra == "docs-build"
Requires-Dist: mkdocs>=1.5.0; extra == "docs-build"
Requires-Dist: mkdocs-material>=9.5.0; extra == "docs-build"
Provides-Extra: web
Requires-Dist: playwright>=1.40.0; extra == "web"
Requires-Dist: beautifulsoup4>=4.12.0; extra == "web"
Requires-Dist: lxml>=4.9.0; extra == "web"
Requires-Dist: nltk>=3.8.1; extra == "web"
Requires-Dist: textblob>=0.17.1; extra == "web"
Requires-Dist: readability-lxml>=0.8.1; extra == "web"
Requires-Dist: axe-selenium-python>=2.1.6; extra == "web"
Requires-Dist: aiofiles>=23.2.1; extra == "web"
Requires-Dist: html5lib>=1.1; extra == "web"
Dynamic: author
Dynamic: author-email
Dynamic: classifier
Dynamic: description
Dynamic: description-content-type
Dynamic: home-page
Dynamic: project-url
Dynamic: provides-extra
Dynamic: requires-dist
Dynamic: requires-python
Dynamic: summary
